mydstools/__init__.py
mydstools/cleaning.py
mydstools/connectors/__init__.py
mydstools/connectors/salesforce.py
mydstools/eda.py
mydstools/feature_engineering.py
mydstools-0.1.5.dist-info/LICENSE
mydstools-0.1.5.dist-info/WHEEL
mydstools-0.1.5.dist-info/METADATA
mydstools-0.1.5.dist-info/RECORD
