Metadata-Version: 2.1
Name: mydstools
Version: 0.1.5
Summary: Data Science Toolbox
License: MIT
Author: Antonio Buzzelli
Requires-Python: >=3.9,<4.0
Classifier: License :: OSI Approved :: MIT License
Classifier: Programming Language :: Python :: 3
Classifier: Programming Language :: Python :: 3.9
Classifier: Programming Language :: Python :: 3.10
Requires-Dist: matplotlib (>=3.6.3,<4.0.0)
Requires-Dist: pandas (>=1.5.3,<2.0.0)
Requires-Dist: seaborn (>=0.12.2,<0.13.0)
Requires-Dist: simple-salesforce (>=1.12.3,<2.0.0)
Requires-Dist: statsmodels (>=0.13.5,<0.14.0)
